vllm_cli/__init__.py
vllm_cli/__main__.py
vllm_cli/cli/__init__.py
vllm_cli/cli/handlers.py
vllm_cli/cli/parser.py
vllm_cli/cli/utils.py
vllm_cli/config/__init__.py
vllm_cli/config/manager.py
vllm_cli/config/persistence.py
vllm_cli/config/profiles.py
vllm_cli/config/schemas.py
vllm_cli/config/shortcuts.py
vllm_cli/errors/__init__.py
vllm_cli/errors/base.py
vllm_cli/errors/config.py
vllm_cli/errors/handlers.py
vllm_cli/errors/model.py
vllm_cli/errors/recovery.py
vllm_cli/errors/retry.py
vllm_cli/errors/server.py
vllm_cli/errors/system.py
vllm_cli/models/__init__.py
vllm_cli/models/cache.py
vllm_cli/models/directories.py
vllm_cli/models/discovery.py
vllm_cli/models/manager.py
vllm_cli/models/manifest.py
vllm_cli/models/metadata.py
vllm_cli/schemas/argument_schema.json
vllm_cli/schemas/categories.json
vllm_cli/schemas/default_profiles.json
vllm_cli/server/__init__.py
vllm_cli/server/discovery.py
vllm_cli/server/manager.py
vllm_cli/server/monitoring.py
vllm_cli/server/process.py
vllm_cli/server/utils.py
vllm_cli/system/__init__.py
vllm_cli/system/capabilities.py
vllm_cli/system/dependencies.py
vllm_cli/system/environment.py
vllm_cli/system/formatting.py
vllm_cli/system/gpu.py
vllm_cli/system/memory.py
vllm_cli/system/requirements.py
vllm_cli/ui/__init__.py
vllm_cli/ui/common.py
vllm_cli/ui/components.py
vllm_cli/ui/custom_config.py
vllm_cli/ui/display.py
vllm_cli/ui/gpu_utils.py
vllm_cli/ui/hf_integration.py
vllm_cli/ui/log_viewer.py
vllm_cli/ui/menu.py
vllm_cli/ui/model_directories.py
vllm_cli/ui/model_manager.py
vllm_cli/ui/navigation.py
vllm_cli/ui/profiles.py
vllm_cli/ui/progress_styles.py
vllm_cli/ui/server_control.py
vllm_cli/ui/server_monitor.py
vllm_cli/ui/settings.py
vllm_cli/ui/shortcuts.py
vllm_cli/ui/system_info.py
vllm_cli/ui/welcome.py
vllm_cli/validation/__init__.py
vllm_cli/validation/base.py
vllm_cli/validation/factory.py
vllm_cli/validation/registry.py
vllm_cli/validation/schema.py
vllm_cli/validation/token.py
vllm_cli/validation/types.py
vllm_cli-0.2.4.dist-info/licenses/LICENSE
vllm_cli-0.2.4.dist-info/METADATA
vllm_cli-0.2.4.dist-info/WHEEL
vllm_cli-0.2.4.dist-info/entry_points.txt
vllm_cli-0.2.4.dist-info/top_level.txt
vllm_cli-0.2.4.dist-info/RECORD
