Metadata-Version: 2.4
Name: vllm-cli
Version: 0.2.4
Summary: A CLI tool to conveniently serve LLMs with vLLM
Author-email: Zexi Chen <zzxxi.chen@gmail.com>
License: MIT
Project-URL: Homepage, https://github.com/Chen-zexi/vllm-cli
Project-URL: Bug Tracker, https://github.com/Chen-zexi/vllm-cli/issues
Classifier: Programming Language :: Python :: 3.9
Classifier: Programming Language :: Python :: 3.10
Classifier: Programming Language :: Python :: 3.11
Classifier: Programming Language :: Python :: 3.12
Classifier: Operating System :: POSIX :: Linux
Classifier: Environment :: Console
Classifier: Intended Audience :: Developers
Classifier: Intended Audience :: Science/Research
Classifier: Topic :: Scientific/Engineering :: Artificial Intelligence
Classifier: Topic :: System :: Distributed Computing
Classifier: Topic :: Utilities
Requires-Python: >=3.9
License-File: LICENSE
Requires-Dist: rich>=13.0
Requires-Dist: inquirer>=3.0
Requires-Dist: click>=8.0
Requires-Dist: psutil>=5.9
Requires-Dist: pydantic>=2.0
Requires-Dist: pyyaml>=6.0
Requires-Dist: hf-model-tool>=0.2.5
Requires-Dist: requests>=2.28.0
Provides-Extra: test
Requires-Dist: pytest>=7.0.0; extra == "test"
Requires-Dist: pytest-cov>=4.0.0; extra == "test"
Requires-Dist: pytest-mock>=3.10.0; extra == "test"
Requires-Dist: requests>=2.28.0; extra == "test"
Provides-Extra: dev
Requires-Dist: pytest>=7.0.0; extra == "dev"
Requires-Dist: black>=23.0.0; extra == "dev"
Requires-Dist: flake8>=6.0.0; extra == "dev"
Requires-Dist: mypy>=1.0.0; extra == "dev"
Dynamic: license-file
